pynvl/__init__.py
pynvl/core.py
pynvl/datetime_ext.py
pynvl/pandas_ext.py
pynvl_lib-1.0.6.dist-info/METADATA
pynvl_lib-1.0.6.dist-info/WHEEL
pynvl_lib-1.0.6.dist-info/top_level.txt
pynvl_lib-1.0.6.dist-info/RECORD
