Metadata-Version: 2.4
Name: pynvl-lib
Version: 1.0.6
Summary: Helper functions for data engineering and analytics workflows in Python, inspired by PL/SQL.
Author: Shane Wilson
License: MIT
Project-URL: Homepage, https://github.com/betterinfotech/pynvl_project
Project-URL: Source, https://github.com/betterinfotech/pynvl_project
Project-URL: Issues, https://github.com/betterinfotech/pynvl_project/issues
Project-URL: Changelog, https://github.com/betterinfotech/pynvl_project/releases
Classifier: Programming Language :: Python :: 3
Classifier: Programming Language :: Python :: 3 :: Only
Classifier: Programming Language :: Python :: 3.10
Classifier: Programming Language :: Python :: 3.11
Classifier: Programming Language :: Python :: 3.12
Classifier: Operating System :: OS Independent
Classifier: Intended Audience :: Developers
Classifier: Topic :: Software Development :: Libraries :: Python Modules
Requires-Python: >=3.10
Provides-Extra: dev
Requires-Dist: pytest>=8; extra == "dev"
Requires-Dist: ruff>=0.5; extra == "dev"
Requires-Dist: mkdocs>=1.6; extra == "dev"
Requires-Dist: mkdocs-material>=9.5; extra == "dev"
